{"status":"done","publicPath":"/static/bundles/","chunks":{"main":[{"name":"static/css/main.e557fd87.css","publicPath":"/static/bundles/static/css/main.e557fd87.css","path":"/home/lin/TodoList/assets/bundles/static/css/main.e557fd87.css"},{"name":"js/main.fbf267b4.js","publicPath":"/static/bundles/js/main.fbf267b4.js","path":"/home/lin/TodoList/assets/bundles/js/main.fbf267b4.js"},{"name":"js/main.fbf267b4.js.map","publicPath":"/static/bundles/js/main.fbf267b4.js.map","path":"/home/lin/TodoList/assets/bundles/js/main.fbf267b4.js.map"}]}}